domainconnect/__init__.py
domainconnect/domainconnect.py
domainconnect/network.py
domain_connect-0.0.11.dist-info/LICENSE
domain_connect-0.0.11.dist-info/METADATA
domain_connect-0.0.11.dist-info/WHEEL
domain_connect-0.0.11.dist-info/top_level.txt
domain_connect-0.0.11.dist-info/RECORD
