Metadata-Version: 2.1
Name: domain_connect
Version: 0.0.11
Summary: Python client library for Domain Connect protocol. See: https://domainconnect.org
Home-page: https://github.com/Domain-Connect/domainconnect_python
Author: Pawel Kowalik
Author-email: pawel-kow@users.noreply.github.com
License: https://github.com/Domain-Connect/domainconnect_python/blob/master/LICENSE
Classifier: Programming Language :: Python :: 2.7
Classifier: Programming Language :: Python :: 3.6
Classifier: Programming Language :: Python :: 3.7
Classifier: Programming Language :: Python :: 3.8
Classifier: Programming Language :: Python :: 3.9
Classifier: Programming Language :: Python :: 3.10
Classifier: Programming Language :: Python :: 3.11
Classifier: Programming Language :: Python :: 3.12
License-File: LICENSE
Requires-Dist: dnspython >=1.16.0
Requires-Dist: publicsuffix >=1.1.0
Requires-Dist: publicsuffixlist >=0.7.7
Requires-Dist: six >=1.12.0
Requires-Dist: future >=0.18.3
Requires-Dist: cryptography >=3.3.2 ; python_version == "2.7"
Requires-Dist: cryptography >=39.0.1 ; python_version > "2.7" and python_version < "3.6"
Requires-Dist: cryptography >=40.0.2 ; python_version >= "3.6" and python_version < "3.7"
Requires-Dist: cryptography >=42.0.0 ; python_version >= "3.7"
Provides-Extra: test
Requires-Dist: unittest2 >=1.1.0 ; extra == 'test'
